{
  "version": "7",
  "dialect": "postgresql",
  "entries": [
    {
      "idx": 0,
      "version": "7",
      "when": 1780564879761,
      "tag": "0000_living_kinsey_walden",
      "breakpoints": true
    },
    {
      "idx": 1,
      "version": "7",
      "when": 1780586502595,
      "tag": "0001_lonely_roxanne_simpson",
      "breakpoints": true
    },
    {
      "idx": 2,
      "version": "7",
      "when": 1780591319603,
      "tag": "0002_early_night_nurse",
      "breakpoints": true
    },
    {
      "idx": 3,
      "version": "7",
      "when": 1780844928966,
      "tag": "0003_shallow_chat",
      "breakpoints": true
    }
  ]
}